kachaka_api/__init__.py
kachaka_api/base.py
kachaka_api/py.typed
kachaka_api/aio/__init__.py
kachaka_api/aio/base.py
kachaka_api/generated/kachaka_api_pb2.py
kachaka_api/generated/kachaka_api_pb2.pyi
kachaka_api/generated/kachaka_api_pb2_grpc.py
kachaka_api/util/command.py
kachaka_api/util/geometry.py
kachaka_api/util/layout.py
kachaka_api/util/vision.py
kachaka_api-3.14.4.0.dist-info/METADATA
kachaka_api-3.14.4.0.dist-info/WHEEL
kachaka_api-3.14.4.0.dist-info/licenses/LICENSE
kachaka_api-3.14.4.0.dist-info/RECORD
