Metadata-Version: 2.4
Name: kachaka-api
Version: 3.14.4.0
Project-URL: Homepage, https://kachaka.life/
Project-URL: Repository, https://github.com/pf-robotics/kachaka-api
Author: Preferred Robotics inc.
License-Expression: Apache-2.0
License-File: LICENSE
Requires-Python: >=3.10
Requires-Dist: grpcio==1.66.1
Requires-Dist: numpy>=2.2.0
Requires-Dist: protobuf>=5.27.2
